[
  {
    "gamedate": "03/28/2025",
    "results": {
      "Colorado Rockies": {
        "game_1": "w"
      }
    }
  },
  {
    "gamedate": "03/27/2025",
    "results": {
      "Colorado Rockies": {
        "game_1": "w",
        "game_2": "l"
      }
    }
  },
  {
    "gamedate": "03/26/2025",
    "results": {
      "Colorado Rockies": {
        "game_1": "l"
      }
    }
  },
  {
    "gamedate": "07/10/2025",
    "results": {
      "Baltimore Orioles": {
        "game_1": "w",
        "game_2": "w"
      },
      "New York Mets": {
        "game_1": "l",
        "game_2": "l"
      },
      "Chicago Cubs": {
        "game_1": "w"
      },
      "Minnesota Twins": {
        "game_1": "l"
      },
      "Cincinnati Reds": {
        "game_1": "w"
      },
      "Miami Marlins": {
        "game_1": "l"
      },
      "New York Yankees": {
        "game_1": "w"
      },
      "Seattle Mariners": {
        "game_1": "l"
      },
      "Boston Red Sox": {
        "game_1": "w"
      },
      "Tampa Bay Rays": {
        "game_1": "l"
      },
      "St. Louis Cardinals": {
        "game_1": "w"
      },
      "Washington Nationals": {
        "game_1": "l"
      },
      "Athletics": {
        "game_1": "w"
      },
      "Atlanta Braves": {
        "game_1": "l"
      },
      "Texas Rangers": {
        "game_1": "w"
      },
      "Los Angeles Angels": {
        "game_1": "l"
      },
      "San Diego Padres": {
        "game_1": "w"
      },
      "Arizona Diamondbacks": {
        "game_1": "l"
      }
    }
  },
  {
    "gamedate": "07/09/2025",
    "results": {
      "Chicago White Sox": {
        "game_1": "w"
      },
      "Toronto Blue Jays": {
        "game_1": "l"
      },
      "Milwaukee Brewers": {
        "game_1": "w"
      },
      "Los Angeles Dodgers": {
        "game_1": "l"
      },
      "Philadelphia Phillies": {
        "game_1": "w"
      },
      "San Francisco Giants": {
        "game_1": "l"
      },
      "Tampa Bay Rays": {
        "game_1": "w"
      },
      "Detroit Tigers": {
        "game_1": "l"
      },
      "New York Yankees": {
        "game_1": "w"
      },
      "Seattle Mariners": {
        "game_1": "l"
      },
      "Boston Red Sox": {
        "game_1": "w"
      },
      "Colorado Rockies": {
        "game_1": "l"
      },
      "Cincinnati Reds": {
        "game_1": "w"
      },
      "Miami Marlins": {
        "game_1": "l"
      },
      "Kansas City Royals": {
        "game_1": "w"
      },
      "Pittsburgh Pirates": {
        "game_1": "l"
      },
      "Minnesota Twins": {
        "game_1": "w"
      },
      "Chicago Cubs": {
        "game_1": "l"
      },
      "Washington Nationals": {
        "game_1": "w"
      },
      "St. Louis Cardinals": {
        "game_1": "l"
      },
      "Cleveland Guardians": {
        "game_1": "w"
      },
      "Houston Astros": {
        "game_1": "l"
      },
      "Los Angeles Angels": {
        "game_1": "w"
      },
      "Texas Rangers": {
        "game_1": "l"
      },
      "Arizona Diamondbacks": {
        "game_1": "w"
      },
      "San Diego Padres": {
        "game_1": "l"
      },
      "Atlanta Braves": {
        "game_1": "w"
      },
      "Athletics": {
        "game_1": "l"
      }
    }
  },
  {
    "gamedate": "07/08/2025",
    "results": {
      "New York Mets": {
        "game_1": "w"
      },
      "Baltimore Orioles": {
        "game_1": "l"
      },
      "Detroit Tigers": {
        "game_1": "w"
      },
      "Tampa Bay Rays": {
        "game_1": "l"
      },
      "New York Yankees": {
        "game_1": "w"
      },
      "Seattle Mariners": {
        "game_1": "l"
      },
      "Boston Red Sox": {
        "game_1": "w"
      },
      "Colorado Rockies": {
        "game_1": "l"
      },
      "Miami Marlins": {
        "game_1": "w"
      },
      "Cincinnati Reds": {
        "game_1": "l"
      },
      "Kansas City Royals": {
        "game_1": "w"
      },
      "Pittsburgh Pirates": {
        "game_1": "l"
      },
      "Minnesota Twins": {
        "game_1": "w"
      },
      "Chicago Cubs": {
        "game_1": "l"
      },
      "Milwaukee Brewers": {
        "game_1": "w"
      },
      "Los Angeles Dodgers": {
        "game_1": "l"
      },
      "St. Louis Cardinals": {
        "game_1": "w"
      },
      "Washington Nationals": {
        "game_1": "l"
      },
      "Cleveland Guardians": {
        "game_1": "w"
      },
      "Houston Astros": {
        "game_1": "l"
      },
      "Texas Rangers": {
        "game_1": "w"
      },
      "Los Angeles Angels": {
        "game_1": "l"
      },
      "San Diego Padres": {
        "game_1": "w"
      },
      "Arizona Diamondbacks": {
        "game_1": "l"
      },
      "San Francisco Giants": {
        "game_1": "w"
      },
      "Philadelphia Phillies": {
        "game_1": "l"
      },
      "Athletics": {
        "game_1": "w"
      },
      "Atlanta Braves": {
        "game_1": "l"
      }
    }
  },
  {
    "gamedate": "07/07/2025",
    "results": {
      "Detroit Tigers": {
        "game_1": "w"
      },
      "Tampa Bay Rays": {
        "game_1": "l"
      },
      "Boston Red Sox": {
        "game_1": "w"
      },
      "Colorado Rockies": {
        "game_1": "l"
      },
      "Miami Marlins": {
        "game_1": "w"
      },
      "Cincinnati Reds": {
        "game_1": "l"
      },
      "Kansas City Royals": {
        "game_1": "w"
      },
      "Pittsburgh Pirates": {
        "game_1": "l"
      },
      "Toronto Blue Jays": {
        "game_1": "w"
      },
      "Chicago White Sox": {
        "game_1": "l"
      },
      "Milwaukee Brewers": {
        "game_1": "w"
      },
      "Los Angeles Dodgers": {
        "game_1": "l"
      },
      "Cleveland Guardians": {
        "game_1": "w"
      },
      "Houston Astros": {
        "game_1": "l"
      },
      "Los Angeles Angels": {
        "game_1": "w"
      },
      "Texas Rangers": {
        "game_1": "l"
      },
      "Arizona Diamondbacks": {
        "game_1": "w"
      },
      "San Diego Padres": {
        "game_1": "l"
      },
      "San Francisco Giants": {
        "game_1": "w"
      },
      "Philadelphia Phillies": {
        "game_1": "l"
      }
    }
  },
  {
    "gamedate": "07/06/2025",
    "results": {
      "Baltimore Orioles": {
        "game_1": "w"
      },
      "Atlanta Braves": {
        "game_1": "l"
      },
      "Boston Red Sox": {
        "game_1": "w"
      },
      "Washington Nationals": {
        "game_1": "l"
      },
      "Philadelphia Phillies": {
        "game_1": "w"
      },
      "Cincinnati Reds": {
        "game_1": "l"
      },
      "Toronto Blue Jays": {
        "game_1": "w"
      },
      "Los Angeles Angels": {
        "game_1": "l"
      },
      "Detroit Tigers": {
        "game_1": "w"
      },
      "Cleveland Guardians": {
        "game_1": "l"
      },
      "New York Yankees": {
        "game_1": "w"
      },
      "New York Mets": {
        "game_1": "l"
      },
      "Milwaukee Brewers": {
        "game_1": "w"
      },
      "Miami Marlins": {
        "game_1": "l"
      },
      "Tampa Bay Rays": {
        "game_1": "w"
      },
      "Minnesota Twins": {
        "game_1": "l"
      },
      "Colorado Rockies": {
        "game_1": "w"
      },
      "Chicago White Sox": {
        "game_1": "l"
      },
      "Kansas City Royals": {
        "game_1": "w"
      },
      "Arizona Diamondbacks": {
        "game_1": "l"
      },
      "Houston Astros": {
        "game_1": "w"
      },
      "Los Angeles Dodgers": {
        "game_1": "l"
      },
      "Seattle Mariners": {
        "game_1": "w"
      },
      "Pittsburgh Pirates": {
        "game_1": "l"
      },
      "Chicago Cubs": {
        "game_1": "w"
      },
      "St. Louis Cardinals": {
        "game_1": "l"
      },
      "San Diego Padres": {
        "game_1": "w"
      },
      "Texas Rangers": {
        "game_1": "l"
      },
      "San Francisco Giants": {
        "game_1": "w"
      },
      "Athletics": {
        "game_1": "l"
      }
    }
  },
  {
    "gamedate": "07/05/2025",
    "results": {
      "Minnesota Twins": {
        "game_1": "w"
      },
      "Tampa Bay Rays": {
        "game_1": "l"
      },
      "St. Louis Cardinals": {
        "game_1": "w"
      },
      "Chicago Cubs": {
        "game_1": "l"
      },
      "Toronto Blue Jays": {
        "game_1": "w"
      },
      "Los Angeles Angels": {
        "game_1": "l"
      },
      "Boston Red Sox": {
        "game_1": "w"
      },
      "Washington Nationals": {
        "game_1": "l"
      },
      "Philadelphia Phillies": {
        "game_1": "w"
      },
      "Cincinnati Reds": {
        "game_1": "l"
      },
      "Arizona Diamondbacks": {
        "game_1": "w"
      },
      "Kansas City Royals": {
        "game_1": "l"
      },
      "Baltimore Orioles": {
        "game_1": "w"
      },
      "Atlanta Braves": {
        "game_1": "l"
      },
      "New York Mets": {
        "game_1": "w"
      },
      "New York Yankees": {
        "game_1": "l"
      },
      "Miami Marlins": {
        "game_1": "w"
      },
      "Milwaukee Brewers": {
        "game_1": "l"
      },
      "Detroit Tigers": {
        "game_1": "w"
      },
      "Cleveland Guardians": {
        "game_1": "l"
      },
      "Houston Astros": {
        "game_1": "w"
      },
      "Los Angeles Dodgers": {
        "game_1": "l"
      },
      "Chicago White Sox": {
        "game_1": "w"
      },
      "Colorado Rockies": {
        "game_1": "l"
      },
      "Texas Rangers": {
        "game_1": "w"
      },
      "San Diego Padres": {
        "game_1": "l"
      },
      "San Francisco Giants": {
        "game_1": "w"
      },
      "Athletics": {
        "game_1": "l"
      },
      "Seattle Mariners": {
        "game_1": "w"
      },
      "Pittsburgh Pirates": {
        "game_1": "l"
      }
    }
  },
  {
    "gamedate": "07/04/2025",
    "results": {
      "Boston Red Sox": {
        "game_1": "w"
      },
      "Washington Nationals": {
        "game_1": "l"
      },
      "Cincinnati Reds": {
        "game_1": "w"
      },
      "Philadelphia Phillies": {
        "game_1": "l"
      },
      "Chicago Cubs": {
        "game_1": "w"
      },
      "St. Louis Cardinals": {
        "game_1": "l"
      },
      "New York Mets": {
        "game_1": "w"
      },
      "New York Yankees": {
        "game_1": "l"
      },
      "Seattle Mariners": {
        "game_1": "w"
      },
      "Pittsburgh Pirates": {
        "game_1": "l"
      },
      "Minnesota Twins": {
        "game_1": "w"
      },
      "Tampa Bay Rays": {
        "game_1": "l"
      },
      "San Diego Padres": {
        "game_1": "w"
      },
      "Texas Rangers": {
        "game_1": "l"
      },
      "Toronto Blue Jays": {
        "game_1": "w"
      },
      "Los Angeles Angels": {
        "game_1": "l"
      },
      "Detroit Tigers": {
        "game_1": "w"
      },
      "Cleveland Guardians": {
        "game_1": "l"
      },
      "Milwaukee Brewers": {
        "game_1": "w"
      },
      "Miami Marlins": {
        "game_1": "l"
      },
      "Baltimore Orioles": {
        "game_1": "w"
      },
      "Atlanta Braves": {
        "game_1": "l"
      },
      "Chicago White Sox": {
        "game_1": "w"
      },
      "Colorado Rockies": {
        "game_1": "l"
      },
      "Houston Astros": {
        "game_1": "w"
      },
      "Los Angeles Dodgers": {
        "game_1": "l"
      },
      "Kansas City Royals": {
        "game_1": "w"
      },
      "Arizona Diamondbacks": {
        "game_1": "l"
      },
      "Athletics": {
        "game_1": "w"
      },
      "San Francisco Giants": {
        "game_1": "l"
      }
    }
  },
  {
    "gamedate": "07/03/2025",
    "results": {
      "Miami Marlins": {
        "game_1": "w"
      },
      "Minnesota Twins": {
        "game_1": "l"
      },
      "Colorado Rockies": {
        "game_1": "w"
      },
      "Houston Astros": {
        "game_1": "l"
      },
      "Washington Nationals": {
        "game_1": "w"
      },
      "Detroit Tigers": {
        "game_1": "l"
      },
      "Toronto Blue Jays": {
        "game_1": "w"
      },
      "New York Yankees": {
        "game_1": "l"
      },
      "New York Mets": {
        "game_1": "w"
      },
      "Milwaukee Brewers": {
        "game_1": "l"
      },
      "Los Angeles Angels": {
        "game_1": "w"
      },
      "Atlanta Braves": {
        "game_1": "l"
      },
      "Chicago Cubs": {
        "game_1": "w"
      },
      "Cleveland Guardians": {
        "game_1": "l"
      },
      "San Francisco Giants": {
        "game_1": "w"
      },
      "Arizona Diamondbacks": {
        "game_1": "l"
      },
      "Kansas City Royals": {
        "game_1": "w"
      },
      "Seattle Mariners": {
        "game_1": "l"
      },
      "Los Angeles Dodgers": {
        "game_1": "w"
      },
      "Chicago White Sox": {
        "game_1": "l"
      }
    }
  },
  {
    "gamedate": "07/02/2025",
    "results": {
      "Tampa Bay Rays": {
        "game_1": "w"
      },
      "Athletics": {
        "game_1": "l"
      },
      "Pittsburgh Pirates": {
        "game_1": "w"
      },
      "St. Louis Cardinals": {
        "game_1": "l"
      },
      "Detroit Tigers": {
        "game_1": "w",
        "game_2": "l"
      },
      "Washington Nationals": {
        "game_1": "l",
        "game_2": "w"
      },
      "San Diego Padres": {
        "game_1": "w",
        "game_2": "l"
      },
      "Philadelphia Phillies": {
        "game_1": "l",
        "game_2": "w"
      },
      "Milwaukee Brewers": {
        "game_1": "w",
        "game_2": "l"
      },
      "New York Mets": {
        "game_1": "l",
        "game_2": "w"
      },
      "Boston Red Sox": {
        "game_1": "w",
        "game_2": "l"
      },
      "Cincinnati Reds": {
        "game_1": "l",
        "game_2": "w"
      },
      "Minnesota Twins": {
        "game_1": "w"
      },
      "Miami Marlins": {
        "game_1": "l"
      },
      "Toronto Blue Jays": {
        "game_1": "w"
      },
      "New York Yankees": {
        "game_1": "l"
      },
      "Atlanta Braves": {
        "game_1": "w"
      },
      "Los Angeles Angels": {
        "game_1": "l"
      },
      "Chicago Cubs": {
        "game_1": "w"
      },
      "Cleveland Guardians": {
        "game_1": "l"
      },
      "Texas Rangers": {
        "game_1": "w"
      },
      "Baltimore Orioles": {
        "game_1": "l"
      },
      "Houston Astros": {
        "game_1": "w"
      },
      "Colorado Rockies": {
        "game_1": "l"
      },
      "Seattle Mariners": {
        "game_1": "w"
      },
      "Kansas City Royals": {
        "game_1": "l"
      },
      "San Francisco Giants": {
        "game_1": "w"
      },
      "Arizona Diamondbacks": {
        "game_1": "l"
      },
      "Los Angeles Dodgers": {
        "game_1": "w"
      },
      "Chicago White Sox": {
        "game_1": "l"
      }
    }
  }
]