{
    "date": "04/14/2026",
    "games": {
        "game_824853": {
            "away_team": "Arizona Diamondbacks",
            "home_team": "Baltimore Orioles",
            "away_lineup": [],
            "home_lineup": [],
            "away_pitcher": {
                "id": 518876,
                "name": "Merrill Kelly",
                "stats": {
                    "strikeouts": 0,
                    "era": "-.--",
                    "ip": "0.0"
                }
            },
            "home_pitcher": {
                "id": 669432,
                "name": "Trevor Rogers",
                "stats": {
                    "strikeouts": 14,
                    "era": "1.89",
                    "ip": "19.0"
                }
            },
            "lineup_hash": "060203a89b1fa7eddd04f99f1546ed2c",
            "lineup_confirmed": false
        },
        "game_824292": {
            "away_team": "Kansas City Royals",
            "home_team": "Detroit Tigers",
            "away_lineup": [],
            "home_lineup": [],
            "away_pitcher": {
                "id": 666142,
                "name": "Cole Ragans",
                "stats": {
                    "strikeouts": 15,
                    "era": "5.91",
                    "ip": "10.2"
                }
            },
            "home_pitcher": {
                "id": 664285,
                "name": "Framber Valdez",
                "stats": {
                    "strikeouts": 12,
                    "era": "4.76",
                    "ip": "17.0"
                }
            },
            "lineup_hash": "14ebe001d48dcdd1ec43162323942d80",
            "lineup_confirmed": false
        },
        "game_823398": {
            "away_team": "Washington Nationals",
            "home_team": "Pittsburgh Pirates",
            "away_lineup": [],
            "home_lineup": [],
            "away_pitcher": {
                "id": 571945,
                "name": "Miles Mikolas",
                "stats": {
                    "strikeouts": 11,
                    "era": "12.41",
                    "ip": "12.1"
                }
            },
            "home_pitcher": {
                "id": 656605,
                "name": "Mitch Keller",
                "stats": {
                    "strikeouts": 11,
                    "era": "1.00",
                    "ip": "18.0"
                }
            },
            "lineup_hash": "abcc7470dcee3a307f32f45935cd0f1e",
            "lineup_confirmed": false
        },
        "game_824531": {
            "away_team": "San Francisco Giants",
            "home_team": "Cincinnati Reds",
            "away_lineup": [],
            "home_lineup": [],
            "away_pitcher": {
                "id": 592662,
                "name": "Robbie Ray",
                "stats": {
                    "strikeouts": 18,
                    "era": "2.08",
                    "ip": "17.1"
                }
            },
            "home_pitcher": {
                "id": 663903,
                "name": "Brady Singer",
                "stats": {
                    "strikeouts": 13,
                    "era": "7.71",
                    "ip": "11.2"
                }
            },
            "lineup_hash": "435876ed73257647c5b2287e47dcc1fc",
            "lineup_confirmed": false
        },
        "game_823478": {
            "away_team": "Chicago Cubs",
            "home_team": "Philadelphia Phillies",
            "away_lineup": [],
            "home_lineup": [],
            "away_pitcher": {
                "id": 702303,
                "name": "Riley Martin",
                "stats": {
                    "strikeouts": 3,
                    "era": "0.00",
                    "ip": "3.1"
                }
            },
            "home_pitcher": {
                "id": 605400,
                "name": "Aaron Nola",
                "stats": {
                    "strikeouts": 19,
                    "era": "3.63",
                    "ip": "17.1"
                }
            },
            "lineup_hash": "6b9eb9fc7b466a689e3e5ac77a66d250",
            "lineup_confirmed": false
        },
        "game_823562": {
            "away_team": "Los Angeles Angels",
            "home_team": "New York Yankees",
            "away_lineup": [],
            "home_lineup": [],
            "away_pitcher": {
                "id": 672282,
                "name": "Reid Detmers",
                "stats": {
                    "strikeouts": 17,
                    "era": "4.60",
                    "ip": "15.2"
                }
            },
            "home_pitcher": {
                "id": 677960,
                "name": "Ryan Weathers",
                "stats": {
                    "strikeouts": 18,
                    "era": "2.81",
                    "ip": "16.0"
                }
            },
            "lineup_hash": "98622e872a41f0537f573415882bd784",
            "lineup_confirmed": false
        },
        "game_824935": {
            "away_team": "Miami Marlins",
            "home_team": "Atlanta Braves",
            "away_lineup": [],
            "home_lineup": [],
            "away_pitcher": {
                "id": 676974,
                "name": "Max Meyer",
                "stats": {
                    "strikeouts": 15,
                    "era": "3.68",
                    "ip": "14.2"
                }
            },
            "home_pitcher": {
                "id": 625643,
                "name": "Reynaldo L\u00f3pez",
                "stats": {
                    "strikeouts": 13,
                    "era": "1.15",
                    "ip": "15.2"
                }
            },
            "lineup_hash": "568968faec4f365e131b9e35effac71b",
            "lineup_confirmed": false
        },
        "game_823723": {
            "away_team": "Boston Red Sox",
            "home_team": "Minnesota Twins",
            "away_lineup": [],
            "home_lineup": [],
            "away_pitcher": {
                "id": 543243,
                "name": "Sonny Gray",
                "stats": {
                    "strikeouts": 10,
                    "era": "2.76",
                    "ip": "16.1"
                }
            },
            "home_pitcher": {
                "id": 690953,
                "name": "Mick Abel",
                "stats": {
                    "strikeouts": 13,
                    "era": "6.08",
                    "ip": "13.1"
                }
            },
            "lineup_hash": "17043125cbb17165d7469d758265851a",
            "lineup_confirmed": false
        },
        "game_824616": {
            "away_team": "Tampa Bay Rays",
            "home_team": "Chicago White Sox",
            "away_lineup": [],
            "home_lineup": [],
            "away_pitcher": {
                "id": 663556,
                "name": "Shane McClanahan",
                "stats": {
                    "strikeouts": 9,
                    "era": "4.15",
                    "ip": "8.2"
                }
            },
            "home_pitcher": {
                "id": 702273,
                "name": "Noah Schultz",
                "stats": {
                    "strikeouts": 0,
                    "era": "-.--",
                    "ip": "0.0"
                }
            },
            "lineup_hash": "bd83923f524b8ffabd8e5fa387447cf4",
            "lineup_confirmed": false
        },
        "game_823802": {
            "away_team": "Toronto Blue Jays",
            "home_team": "Milwaukee Brewers",
            "away_lineup": [],
            "home_lineup": [],
            "away_pitcher": {
                "id": 592332,
                "name": "Kevin Gausman",
                "stats": {
                    "strikeouts": 26,
                    "era": "2.08",
                    "ip": "17.1"
                }
            },
            "home_pitcher": {
                "id": 694819,
                "name": "Jacob Misiorowski",
                "stats": {
                    "strikeouts": 28,
                    "era": "3.31",
                    "ip": "16.1"
                }
            },
            "lineup_hash": "7784bcb0ecaf1b5d7b3139454a799579",
            "lineup_confirmed": false
        },
        "game_823072": {
            "away_team": "Cleveland Guardians",
            "home_team": "St. Louis Cardinals",
            "away_lineup": [],
            "home_lineup": [],
            "away_pitcher": {
                "id": 676282,
                "name": "Joey Cantillo",
                "stats": {
                    "strikeouts": 20,
                    "era": "2.45",
                    "ip": "14.2"
                }
            },
            "home_pitcher": {
                "id": 700241,
                "name": "Michael McGreevy",
                "stats": {
                    "strikeouts": 10,
                    "era": "2.16",
                    "ip": "16.2"
                }
            },
            "lineup_hash": "d81f23e8356cb8bf15e58ff1fe3d6b40",
            "lineup_confirmed": false
        },
        "game_824210": {
            "away_team": "Colorado Rockies",
            "home_team": "Houston Astros",
            "away_lineup": [],
            "home_lineup": [],
            "away_pitcher": null,
            "home_pitcher": {
                "id": 676467,
                "name": "Colton Gordon",
                "stats": {
                    "strikeouts": 0,
                    "era": "-.--",
                    "ip": "0.0"
                }
            },
            "lineup_hash": "9df9d8f179c42e6ab82f1a333764c48b",
            "lineup_confirmed": false
        },
        "game_823315": {
            "away_team": "Seattle Mariners",
            "home_team": "San Diego Padres",
            "away_lineup": [],
            "home_lineup": [],
            "away_pitcher": {
                "id": 693433,
                "name": "Bryan Woo",
                "stats": {
                    "strikeouts": 17,
                    "era": "1.50",
                    "ip": "18.0"
                }
            },
            "home_pitcher": {
                "id": 650633,
                "name": "Michael King",
                "stats": {
                    "strikeouts": 15,
                    "era": "3.24",
                    "ip": "16.2"
                }
            },
            "lineup_hash": "515de1e8ae511ea27fdc7372aff33898",
            "lineup_confirmed": false
        },
        "game_825022": {
            "away_team": "Texas Rangers",
            "home_team": "Athletics",
            "away_lineup": [],
            "home_lineup": [],
            "away_pitcher": {
                "id": 669022,
                "name": "MacKenzie Gore",
                "stats": {
                    "strikeouts": 25,
                    "era": "2.76",
                    "ip": "16.1"
                }
            },
            "home_pitcher": {
                "id": 605488,
                "name": "Jeffrey Springs",
                "stats": {
                    "strikeouts": 15,
                    "era": "1.47",
                    "ip": "18.1"
                }
            },
            "lineup_hash": "626a4ae26097f2d787246531860ed343",
            "lineup_confirmed": false
        },
        "game_823965": {
            "away_team": "New York Mets",
            "home_team": "Los Angeles Dodgers",
            "away_lineup": [],
            "home_lineup": [],
            "away_pitcher": {
                "id": 690997,
                "name": "Nolan McLean",
                "stats": {
                    "strikeouts": 20,
                    "era": "2.70",
                    "ip": "16.2"
                }
            },
            "home_pitcher": {
                "id": 808967,
                "name": "Yoshinobu Yamamoto",
                "stats": {
                    "strikeouts": 14,
                    "era": "2.50",
                    "ip": "18.0"
                }
            },
            "lineup_hash": "34c01fd5fee5180c9c405f1ed3fa2560",
            "lineup_confirmed": false
        }
    }
}