{
    "date": "04/29/2026",
    "games": {
        "824445": {
            "away_team": "Tampa Bay Rays",
            "home_team": "Cleveland Guardians",
            "away_lineup": [
                {
                    "id": 670764,
                    "name": "Taylor Walls",
                    "position": "SS",
                    "stats": {
                        "runs": 9,
                        "doubles": 2,
                        "triples": 0,
                        "home_runs": 0,
                        "hits": 11,
                        "steals": 4,
                        "rbi": 4
                    }
                },
                {
                    "id": 680700,
                    "name": "Richie Palacios",
                    "position": "2B",
                    "stats": {
                        "runs": 8,
                        "doubles": 1,
                        "triples": 0,
                        "home_runs": 1,
                        "hits": 10,
                        "steals": 4,
                        "rbi": 5
                    }
                },
                {
                    "id": 641584,
                    "name": "Jake Fraley",
                    "position": "RF",
                    "stats": {
                        "runs": 4,
                        "doubles": 6,
                        "triples": 0,
                        "home_runs": 2,
                        "hits": 14,
                        "steals": 2,
                        "rbi": 4
                    }
                },
                {
                    "id": 802415,
                    "name": "Chandler Simpson",
                    "position": "LF",
                    "stats": {
                        "runs": 14,
                        "doubles": 1,
                        "triples": 2,
                        "home_runs": 0,
                        "hits": 35,
                        "steals": 10,
                        "rbi": 6
                    }
                },
                {
                    "id": 676439,
                    "name": "Hunter Feduccia",
                    "position": "C",
                    "stats": {
                        "runs": 4,
                        "doubles": 0,
                        "triples": 0,
                        "home_runs": 0,
                        "hits": 7,
                        "steals": 0,
                        "rbi": 4
                    }
                },
                {
                    "id": 666018,
                    "name": "Jonathan Aranda",
                    "position": "1B",
                    "stats": {
                        "runs": 17,
                        "doubles": 4,
                        "triples": 0,
                        "home_runs": 7,
                        "hits": 24,
                        "steals": 0,
                        "rbi": 25
                    }
                },
                {
                    "id": 650490,
                    "name": "Yandy D\u00edaz",
                    "position": "DH",
                    "stats": {
                        "runs": 17,
                        "doubles": 3,
                        "triples": 1,
                        "home_runs": 4,
                        "hits": 36,
                        "steals": 1,
                        "rbi": 20
                    }
                },
                {
                    "id": 691406,
                    "name": "Junior Caminero",
                    "position": "3B",
                    "stats": {
                        "runs": 17,
                        "doubles": 3,
                        "triples": 0,
                        "home_runs": 8,
                        "hits": 29,
                        "steals": 0,
                        "rbi": 15
                    }
                },
                {
                    "id": 656775,
                    "name": "Cedric Mullins",
                    "position": "CF",
                    "stats": {
                        "runs": 8,
                        "doubles": 2,
                        "triples": 1,
                        "home_runs": 2,
                        "hits": 12,
                        "steals": 6,
                        "rbi": 8
                    }
                }
            ],
            "home_lineup": [
                {
                    "id": 800050,
                    "name": "Chase DeLauter",
                    "position": "RF",
                    "stats": {
                        "runs": 12,
                        "doubles": 6,
                        "triples": 1,
                        "home_runs": 5,
                        "hits": 24,
                        "steals": 0,
                        "rbi": 16
                    }
                },
                {
                    "id": 683953,
                    "name": "Travis Bazzana",
                    "position": "2B",
                    "stats": {
                        "runs": 0,
                        "doubles": 0,
                        "triples": 0,
                        "home_runs": 0,
                        "hits": 0,
                        "steals": 0,
                        "rbi": 0
                    }
                },
                {
                    "id": 682177,
                    "name": "Daniel Schneemann",
                    "position": "3B",
                    "stats": {
                        "runs": 12,
                        "doubles": 7,
                        "triples": 0,
                        "home_runs": 4,
                        "hits": 23,
                        "steals": 1,
                        "rbi": 14
                    }
                },
                {
                    "id": 677587,
                    "name": "Brayan Rocchio",
                    "position": "SS",
                    "stats": {
                        "runs": 11,
                        "doubles": 3,
                        "triples": 0,
                        "home_runs": 3,
                        "hits": 25,
                        "steals": 1,
                        "rbi": 17
                    }
                },
                {
                    "id": 666310,
                    "name": "Bo Naylor",
                    "position": "C",
                    "stats": {
                        "runs": 1,
                        "doubles": 1,
                        "triples": 0,
                        "home_runs": 1,
                        "hits": 8,
                        "steals": 0,
                        "rbi": 3
                    }
                },
                {
                    "id": 608070,
                    "name": "Jos\u00e9 Ram\u00edrez",
                    "position": "DH",
                    "stats": {
                        "runs": 19,
                        "doubles": 6,
                        "triples": 0,
                        "home_runs": 6,
                        "hits": 25,
                        "steals": 11,
                        "rbi": 12
                    }
                },
                {
                    "id": 680757,
                    "name": "Steven Kwan",
                    "position": "CF",
                    "stats": {
                        "runs": 10,
                        "doubles": 4,
                        "triples": 0,
                        "home_runs": 1,
                        "hits": 24,
                        "steals": 2,
                        "rbi": 8
                    }
                },
                {
                    "id": 682657,
                    "name": "Angel Mart\u00ednez",
                    "position": "LF",
                    "stats": {
                        "runs": 12,
                        "doubles": 6,
                        "triples": 0,
                        "home_runs": 5,
                        "hits": 25,
                        "steals": 5,
                        "rbi": 15
                    }
                },
                {
                    "id": 700932,
                    "name": "Kyle Manzardo",
                    "position": "1B",
                    "stats": {
                        "runs": 3,
                        "doubles": 2,
                        "triples": 0,
                        "home_runs": 1,
                        "hits": 16,
                        "steals": 0,
                        "rbi": 6
                    }
                }
            ],
            "away_pitcher": {
                "id": 656876,
                "name": "Drew Rasmussen",
                "stats": {
                    "strikeouts": 26,
                    "era": "2.45",
                    "ip": "25.2"
                }
            },
            "home_pitcher": {
                "id": 668909,
                "name": "Gavin Williams",
                "stats": {
                    "strikeouts": 44,
                    "era": "3.28",
                    "ip": "35.2"
                }
            },
            "lineup_hash": "888982c27f2d991fd52a6e4d032aff10"
        },
        "824608": {
            "away_team": "Los Angeles Angels",
            "home_team": "Chicago White Sox",
            "away_lineup": [
                {
                    "id": 624428,
                    "name": "Adam Frazier",
                    "position": "2B",
                    "stats": {
                        "runs": 12,
                        "doubles": 3,
                        "triples": 1,
                        "home_runs": 1,
                        "hits": 13,
                        "steals": 0,
                        "rbi": 5
                    }
                },
                {
                    "id": 687263,
                    "name": "Zach Neto",
                    "position": "SS",
                    "stats": {
                        "runs": 21,
                        "doubles": 8,
                        "triples": 0,
                        "home_runs": 5,
                        "hits": 30,
                        "steals": 5,
                        "rbi": 15
                    }
                },
                {
                    "id": 624585,
                    "name": "Jorge Soler",
                    "position": "RF",
                    "stats": {
                        "runs": 15,
                        "doubles": 5,
                        "triples": 0,
                        "home_runs": 6,
                        "hits": 23,
                        "steals": 0,
                        "rbi": 23
                    }
                },
                {
                    "id": 660162,
                    "name": "Yo\u00e1n Moncada",
                    "position": "3B",
                    "stats": {
                        "runs": 9,
                        "doubles": 0,
                        "triples": 1,
                        "home_runs": 3,
                        "hits": 15,
                        "steals": 0,
                        "rbi": 9
                    }
                },
                {
                    "id": 518595,
                    "name": "Travis d'Arnaud",
                    "position": "C",
                    "stats": {
                        "runs": 4,
                        "doubles": 1,
                        "triples": 0,
                        "home_runs": 0,
                        "hits": 4,
                        "steals": 0,
                        "rbi": 0
                    }
                },
                {
                    "id": 545361,
                    "name": "Mike Trout",
                    "position": "DH",
                    "stats": {
                        "runs": 28,
                        "doubles": 5,
                        "triples": 0,
                        "home_runs": 9,
                        "hits": 26,
                        "steals": 5,
                        "rbi": 20
                    }
                },
                {
                    "id": 666176,
                    "name": "Jo Adell",
                    "position": "LF",
                    "stats": {
                        "runs": 13,
                        "doubles": 2,
                        "triples": 0,
                        "home_runs": 4,
                        "hits": 33,
                        "steals": 2,
                        "rbi": 19
                    }
                },
                {
                    "id": 687093,
                    "name": "Vaughn Grissom",
                    "position": "1B",
                    "stats": {
                        "runs": 5,
                        "doubles": 4,
                        "triples": 0,
                        "home_runs": 0,
                        "hits": 12,
                        "steals": 0,
                        "rbi": 4
                    }
                },
                {
                    "id": 666139,
                    "name": "Josh Lowe",
                    "position": "CF",
                    "stats": {
                        "runs": 7,
                        "doubles": 1,
                        "triples": 0,
                        "home_runs": 4,
                        "hits": 14,
                        "steals": 1,
                        "rbi": 10
                    }
                }
            ],
            "home_lineup": [
                {
                    "id": 682668,
                    "name": "Luisangel Acu\u00f1a",
                    "position": "CF",
                    "stats": {
                        "runs": 7,
                        "doubles": 1,
                        "triples": 0,
                        "home_runs": 0,
                        "hits": 13,
                        "steals": 6,
                        "rbi": 3
                    }
                },
                {
                    "id": 808959,
                    "name": "Munetaka Murakami",
                    "position": "1B",
                    "stats": {
                        "runs": 22,
                        "doubles": 0,
                        "triples": 0,
                        "home_runs": 12,
                        "hits": 26,
                        "steals": 0,
                        "rbi": 23
                    }
                },
                {
                    "id": 805367,
                    "name": "Chase Meidroth",
                    "position": "2B",
                    "stats": {
                        "runs": 17,
                        "doubles": 5,
                        "triples": 0,
                        "home_runs": 1,
                        "hits": 27,
                        "steals": 1,
                        "rbi": 3
                    }
                },
                {
                    "id": 695657,
                    "name": "Colson Montgomery",
                    "position": "SS",
                    "stats": {
                        "runs": 13,
                        "doubles": 5,
                        "triples": 0,
                        "home_runs": 8,
                        "hits": 25,
                        "steals": 1,
                        "rbi": 20
                    }
                },
                {
                    "id": 669720,
                    "name": "Austin Hays",
                    "position": "DH",
                    "stats": {
                        "runs": 2,
                        "doubles": 1,
                        "triples": 0,
                        "home_runs": 1,
                        "hits": 7,
                        "steals": 0,
                        "rbi": 6
                    }
                },
                {
                    "id": 700337,
                    "name": "Edgar Quero",
                    "position": "C",
                    "stats": {
                        "runs": 3,
                        "doubles": 1,
                        "triples": 0,
                        "home_runs": 0,
                        "hits": 11,
                        "steals": 1,
                        "rbi": 4
                    }
                },
                {
                    "id": 803011,
                    "name": "Sam Antonacci",
                    "position": "LF",
                    "stats": {
                        "runs": 5,
                        "doubles": 1,
                        "triples": 1,
                        "home_runs": 1,
                        "hits": 8,
                        "steals": 0,
                        "rbi": 5
                    }
                },
                {
                    "id": 656537,
                    "name": "Derek Hill",
                    "position": "RF",
                    "stats": {
                        "runs": 5,
                        "doubles": 0,
                        "triples": 0,
                        "home_runs": 1,
                        "hits": 8,
                        "steals": 4,
                        "rbi": 1
                    }
                },
                {
                    "id": 678246,
                    "name": "Miguel Vargas",
                    "position": "3B",
                    "stats": {
                        "runs": 21,
                        "doubles": 4,
                        "triples": 1,
                        "home_runs": 6,
                        "hits": 22,
                        "steals": 5,
                        "rbi": 14
                    }
                }
            ],
            "away_pitcher": {
                "id": 579328,
                "name": "Yusei Kikuchi",
                "stats": {
                    "strikeouts": 32,
                    "era": "6.21",
                    "ip": "29.0"
                }
            },
            "home_pitcher": {
                "id": 607200,
                "name": "Erick Fedde",
                "stats": {
                    "strikeouts": 16,
                    "era": "3.42",
                    "ip": "26.1"
                }
            },
            "lineup_hash": "f1a3ab9bda3fcb5b8692581d35f25a0c"
        },
        "823717": {
            "away_team": "Seattle Mariners",
            "home_team": "Minnesota Twins",
            "away_lineup": [
                {
                    "id": 647304,
                    "name": "Josh Naylor",
                    "position": "1B",
                    "stats": {
                        "runs": 8,
                        "doubles": 2,
                        "triples": 0,
                        "home_runs": 4,
                        "hits": 24,
                        "steals": 4,
                        "rbi": 15
                    }
                },
                {
                    "id": 702284,
                    "name": "Cole Young",
                    "position": "2B",
                    "stats": {
                        "runs": 19,
                        "doubles": 3,
                        "triples": 1,
                        "home_runs": 3,
                        "hits": 30,
                        "steals": 1,
                        "rbi": 16
                    }
                },
                {
                    "id": 669717,
                    "name": "Will Wilson",
                    "position": "3B",
                    "stats": {
                        "runs": 1,
                        "doubles": 0,
                        "triples": 0,
                        "home_runs": 1,
                        "hits": 1,
                        "steals": 0,
                        "rbi": 2
                    }
                },
                {
                    "id": 668227,
                    "name": "Randy Arozarena",
                    "position": "LF",
                    "stats": {
                        "runs": 21,
                        "doubles": 9,
                        "triples": 1,
                        "home_runs": 2,
                        "hits": 33,
                        "steals": 7,
                        "rbi": 11
                    }
                },
                {
                    "id": 641487,
                    "name": "J.P. Crawford",
                    "position": "SS",
                    "stats": {
                        "runs": 12,
                        "doubles": 3,
                        "triples": 0,
                        "home_runs": 1,
                        "hits": 14,
                        "steals": 1,
                        "rbi": 6
                    }
                },
                {
                    "id": 686527,
                    "name": "Dominic Canzone",
                    "position": "DH",
                    "stats": {
                        "runs": 9,
                        "doubles": 6,
                        "triples": 0,
                        "home_runs": 3,
                        "hits": 17,
                        "steals": 1,
                        "rbi": 12
                    }
                },
                {
                    "id": 663728,
                    "name": "Cal Raleigh",
                    "position": "C",
                    "stats": {
                        "runs": 13,
                        "doubles": 4,
                        "triples": 0,
                        "home_runs": 7,
                        "hits": 24,
                        "steals": 2,
                        "rbi": 17
                    }
                },
                {
                    "id": 677594,
                    "name": "Julio Rodr\u00edguez",
                    "position": "CF",
                    "stats": {
                        "runs": 14,
                        "doubles": 6,
                        "triples": 0,
                        "home_runs": 2,
                        "hits": 31,
                        "steals": 3,
                        "rbi": 12
                    }
                },
                {
                    "id": 670042,
                    "name": "Luke Raley",
                    "position": "RF",
                    "stats": {
                        "runs": 11,
                        "doubles": 4,
                        "triples": 1,
                        "home_runs": 5,
                        "hits": 21,
                        "steals": 0,
                        "rbi": 13
                    }
                }
            ],
            "home_lineup": [
                {
                    "id": 665019,
                    "name": "Kody Clemens",
                    "position": "1B",
                    "stats": {
                        "runs": 5,
                        "doubles": 2,
                        "triples": 0,
                        "home_runs": 3,
                        "hits": 12,
                        "steals": 4,
                        "rbi": 8
                    }
                },
                {
                    "id": 686797,
                    "name": "Brooks Lee",
                    "position": "SS",
                    "stats": {
                        "runs": 12,
                        "doubles": 2,
                        "triples": 0,
                        "home_runs": 5,
                        "hits": 22,
                        "steals": 1,
                        "rbi": 15
                    }
                },
                {
                    "id": 605137,
                    "name": "Josh Bell",
                    "position": "DH",
                    "stats": {
                        "runs": 20,
                        "doubles": 5,
                        "triples": 0,
                        "home_runs": 3,
                        "hits": 24,
                        "steals": 0,
                        "rbi": 16
                    }
                },
                {
                    "id": 680777,
                    "name": "Ryan Jeffers",
                    "position": "C",
                    "stats": {
                        "runs": 14,
                        "doubles": 2,
                        "triples": 1,
                        "home_runs": 3,
                        "hits": 20,
                        "steals": 1,
                        "rbi": 18
                    }
                },
                {
                    "id": 668904,
                    "name": "Royce Lewis",
                    "position": "3B",
                    "stats": {
                        "runs": 7,
                        "doubles": 2,
                        "triples": 0,
                        "home_runs": 3,
                        "hits": 12,
                        "steals": 2,
                        "rbi": 10
                    }
                },
                {
                    "id": 663616,
                    "name": "Trevor Larnach",
                    "position": "LF",
                    "stats": {
                        "runs": 11,
                        "doubles": 4,
                        "triples": 1,
                        "home_runs": 1,
                        "hits": 16,
                        "steals": 1,
                        "rbi": 8
                    }
                },
                {
                    "id": 621439,
                    "name": "Byron Buxton",
                    "position": "CF",
                    "stats": {
                        "runs": 21,
                        "doubles": 4,
                        "triples": 1,
                        "home_runs": 7,
                        "hits": 27,
                        "steals": 1,
                        "rbi": 10
                    }
                },
                {
                    "id": 670242,
                    "name": "Matt Wallner",
                    "position": "RF",
                    "stats": {
                        "runs": 12,
                        "doubles": 2,
                        "triples": 0,
                        "home_runs": 3,
                        "hits": 16,
                        "steals": 0,
                        "rbi": 7
                    }
                },
                {
                    "id": 807712,
                    "name": "Luke Keaschall",
                    "position": "2B",
                    "stats": {
                        "runs": 12,
                        "doubles": 4,
                        "triples": 0,
                        "home_runs": 1,
                        "hits": 25,
                        "steals": 7,
                        "rbi": 13
                    }
                }
            ],
            "away_pitcher": {
                "id": 669923,
                "name": "George Kirby",
                "stats": {
                    "strikeouts": 29,
                    "era": "2.97",
                    "ip": "39.1"
                }
            },
            "home_pitcher": {
                "id": 671737,
                "name": "Taj Bradley",
                "stats": {
                    "strikeouts": 37,
                    "era": "2.91",
                    "ip": "34.0"
                }
            },
            "lineup_hash": "7f5ba9fe486f3a69353010c711bb7ef7"
        },
        "822907": {
            "away_team": "New York Yankees",
            "home_team": "Texas Rangers",
            "away_lineup": [
                {
                    "id": 676609,
                    "name": "Jos\u00e9 Caballero",
                    "position": "SS",
                    "stats": {
                        "runs": 12,
                        "doubles": 5,
                        "triples": 0,
                        "home_runs": 3,
                        "hits": 27,
                        "steals": 12,
                        "rbi": 11
                    }
                },
                {
                    "id": 592450,
                    "name": "Aaron Judge",
                    "position": "DH",
                    "stats": {
                        "runs": 25,
                        "doubles": 5,
                        "triples": 0,
                        "home_runs": 12,
                        "hits": 28,
                        "steals": 5,
                        "rbi": 20
                    }
                },
                {
                    "id": 641857,
                    "name": "Ryan McMahon",
                    "position": "3B",
                    "stats": {
                        "runs": 6,
                        "doubles": 0,
                        "triples": 0,
                        "home_runs": 2,
                        "hits": 12,
                        "steals": 0,
                        "rbi": 7
                    }
                },
                {
                    "id": 691176,
                    "name": "Jasson Dom\u00ednguez",
                    "position": "LF",
                    "stats": {
                        "runs": 0,
                        "doubles": 0,
                        "triples": 0,
                        "home_runs": 0,
                        "hits": 1,
                        "steals": 0,
                        "rbi": 0
                    }
                },
                {
                    "id": 700250,
                    "name": "Ben Rice",
                    "position": "1B",
                    "stats": {
                        "runs": 26,
                        "doubles": 8,
                        "triples": 0,
                        "home_runs": 10,
                        "hits": 29,
                        "steals": 1,
                        "rbi": 23
                    }
                },
                {
                    "id": 641555,
                    "name": "J.C. Escarra",
                    "position": "C",
                    "stats": {
                        "runs": 3,
                        "doubles": 2,
                        "triples": 1,
                        "home_runs": 0,
                        "hits": 6,
                        "steals": 0,
                        "rbi": 5
                    }
                },
                {
                    "id": 641355,
                    "name": "Cody Bellinger",
                    "position": "RF",
                    "stats": {
                        "runs": 18,
                        "doubles": 4,
                        "triples": 1,
                        "home_runs": 3,
                        "hits": 25,
                        "steals": 3,
                        "rbi": 15
                    }
                },
                {
                    "id": 665862,
                    "name": "Jazz Chisholm Jr.",
                    "position": "2B",
                    "stats": {
                        "runs": 13,
                        "doubles": 5,
                        "triples": 0,
                        "home_runs": 3,
                        "hits": 22,
                        "steals": 9,
                        "rbi": 10
                    }
                },
                {
                    "id": 663757,
                    "name": "Trent Grisham",
                    "position": "CF",
                    "stats": {
                        "runs": 15,
                        "doubles": 1,
                        "triples": 1,
                        "home_runs": 4,
                        "hits": 14,
                        "steals": 1,
                        "rbi": 16
                    }
                }
            ],
            "home_lineup": [
                {
                    "id": 694497,
                    "name": "Evan Carter",
                    "position": "CF",
                    "stats": {
                        "runs": 10,
                        "doubles": 4,
                        "triples": 0,
                        "home_runs": 3,
                        "hits": 17,
                        "steals": 5,
                        "rbi": 9
                    }
                },
                {
                    "id": 669394,
                    "name": "Jake Burger",
                    "position": "1B",
                    "stats": {
                        "runs": 11,
                        "doubles": 4,
                        "triples": 0,
                        "home_runs": 5,
                        "hits": 26,
                        "steals": 0,
                        "rbi": 19
                    }
                },
                {
                    "id": 696030,
                    "name": "Alejandro Osuna",
                    "position": "LF",
                    "stats": {
                        "runs": 1,
                        "doubles": 0,
                        "triples": 0,
                        "home_runs": 0,
                        "hits": 3,
                        "steals": 0,
                        "rbi": 1
                    }
                },
                {
                    "id": 592626,
                    "name": "Joc Pederson",
                    "position": "DH",
                    "stats": {
                        "runs": 11,
                        "doubles": 1,
                        "triples": 0,
                        "home_runs": 2,
                        "hits": 15,
                        "steals": 0,
                        "rbi": 5
                    }
                },
                {
                    "id": 608369,
                    "name": "Corey Seager",
                    "position": "SS",
                    "stats": {
                        "runs": 19,
                        "doubles": 5,
                        "triples": 0,
                        "home_runs": 6,
                        "hits": 23,
                        "steals": 1,
                        "rbi": 17
                    }
                },
                {
                    "id": 673962,
                    "name": "Josh Jung",
                    "position": "3B",
                    "stats": {
                        "runs": 12,
                        "doubles": 11,
                        "triples": 0,
                        "home_runs": 4,
                        "hits": 31,
                        "steals": 1,
                        "rbi": 15
                    }
                },
                {
                    "id": 543309,
                    "name": "Kyle Higashioka",
                    "position": "C",
                    "stats": {
                        "runs": 5,
                        "doubles": 1,
                        "triples": 0,
                        "home_runs": 1,
                        "hits": 9,
                        "steals": 0,
                        "rbi": 3
                    }
                },
                {
                    "id": 677649,
                    "name": "Ezequiel Duran",
                    "position": "2B",
                    "stats": {
                        "runs": 7,
                        "doubles": 4,
                        "triples": 0,
                        "home_runs": 1,
                        "hits": 15,
                        "steals": 3,
                        "rbi": 8
                    }
                },
                {
                    "id": 607043,
                    "name": "Brandon Nimmo",
                    "position": "RF",
                    "stats": {
                        "runs": 14,
                        "doubles": 7,
                        "triples": 1,
                        "home_runs": 4,
                        "hits": 35,
                        "steals": 1,
                        "rbi": 12
                    }
                }
            ],
            "away_pitcher": {
                "id": 695684,
                "name": "Elmer Rodr\u00edguez",
                "stats": {
                    "strikeouts": 0,
                    "era": "-.--",
                    "ip": "0.0"
                }
            },
            "home_pitcher": {
                "id": 543135,
                "name": "Nathan Eovaldi",
                "stats": {
                    "strikeouts": 32,
                    "era": "5.79",
                    "ip": "32.2"
                }
            },
            "lineup_hash": "49335fc36c25c23451715cbb8cfeccda"
        },
        "822821": {
            "away_team": "Boston Red Sox",
            "home_team": "Toronto Blue Jays",
            "away_lineup": [],
            "home_lineup": [],
            "away_pitcher": {
                "id": 678394,
                "name": "Brayan Bello",
                "stats": {
                    "strikeouts": 15,
                    "era": "9.00",
                    "ip": "22.0"
                }
            },
            "home_pitcher": {
                "id": 641778,
                "name": "Eric Lauer",
                "stats": {
                    "strikeouts": 19,
                    "era": "6.75",
                    "ip": "22.2"
                }
            },
            "lineup_hash": "fbacc58c8215c6247a853de8f6db6971"
        },
        "823958": {
            "away_team": "Miami Marlins",
            "home_team": "Los Angeles Dodgers",
            "away_lineup": [],
            "home_lineup": [],
            "away_pitcher": {
                "id": 645261,
                "name": "Sandy Alcantara",
                "stats": {
                    "strikeouts": 27,
                    "era": "3.05",
                    "ip": "41.1"
                }
            },
            "home_pitcher": {
                "id": 607192,
                "name": "Tyler Glasnow",
                "stats": {
                    "strikeouts": 38,
                    "era": "2.45",
                    "ip": "33.0"
                }
            },
            "lineup_hash": "00156252253b84ef0da4ab65b1dc955d"
        },
        "823312": {
            "away_team": "Chicago Cubs",
            "home_team": "San Diego Padres",
            "away_lineup": [],
            "home_lineup": [],
            "away_pitcher": {
                "id": 592791,
                "name": "Jameson Taillon",
                "stats": {
                    "strikeouts": 25,
                    "era": "4.55",
                    "ip": "27.2"
                }
            },
            "home_pitcher": {
                "id": 663362,
                "name": "Matt Waldron",
                "stats": {
                    "strikeouts": 7,
                    "era": "12.46",
                    "ip": "8.2"
                }
            },
            "lineup_hash": "bcead9dc52e7693f6a2d29aa2f9ee069"
        },
        "824850": {
            "away_team": "Houston Astros",
            "home_team": "Baltimore Orioles",
            "away_lineup": [],
            "home_lineup": [],
            "away_pitcher": {
                "id": 663567,
                "name": "Peter Lambert",
                "stats": {
                    "strikeouts": 16,
                    "era": "3.27",
                    "ip": "11.0"
                }
            },
            "home_pitcher": {
                "id": 605135,
                "name": "Chris Bassitt",
                "stats": {
                    "strikeouts": 10,
                    "era": "6.75",
                    "ip": "21.1"
                }
            },
            "lineup_hash": "397d795f7e74d0e24e87dd458911eb04"
        },
        "824525": {
            "away_team": "Colorado Rockies",
            "home_team": "Cincinnati Reds",
            "away_lineup": [],
            "home_lineup": [],
            "away_pitcher": {
                "id": 608372,
                "name": "Tomoyuki Sugano",
                "stats": {
                    "strikeouts": 19,
                    "era": "3.42",
                    "ip": "26.1"
                }
            },
            "home_pitcher": {
                "id": 682227,
                "name": "Brandon Williamson",
                "stats": {
                    "strikeouts": 15,
                    "era": "5.40",
                    "ip": "25.0"
                }
            },
            "lineup_hash": "d387d6020609221798b78edae782f201"
        },
        "823392": {
            "away_team": "St. Louis Cardinals",
            "home_team": "Pittsburgh Pirates",
            "away_lineup": [],
            "home_lineup": [],
            "away_pitcher": {
                "id": 669467,
                "name": "Andre Pallante",
                "stats": {
                    "strikeouts": 20,
                    "era": "4.26",
                    "ip": "25.1"
                }
            },
            "home_pitcher": {
                "id": 696149,
                "name": "Bubba Chandler",
                "stats": {
                    "strikeouts": 21,
                    "era": "4.88",
                    "ip": "24.0"
                }
            },
            "lineup_hash": "97fdcebb3c31a44cd2018aeb50d98e84"
        },
        "823471": {
            "away_team": "San Francisco Giants",
            "home_team": "Philadelphia Phillies",
            "away_lineup": [],
            "home_lineup": [],
            "away_pitcher": {
                "id": 657277,
                "name": "Logan Webb",
                "stats": {
                    "strikeouts": 32,
                    "era": "4.86",
                    "ip": "37.0"
                }
            },
            "home_pitcher": {
                "id": 650911,
                "name": "Cristopher S\u00e1nchez",
                "stats": {
                    "strikeouts": 43,
                    "era": "2.94",
                    "ip": "33.2"
                }
            },
            "lineup_hash": "9631919bb1a9151ddf37e93839b2dbf6"
        },
        "823633": {
            "away_team": "Washington Nationals",
            "home_team": "New York Mets",
            "away_lineup": [],
            "home_lineup": [],
            "away_pitcher": {
                "id": 676917,
                "name": "Cade Cavalli",
                "stats": {
                    "strikeouts": 28,
                    "era": "4.01",
                    "ip": "24.2"
                }
            },
            "home_pitcher": {
                "id": 656849,
                "name": "David Peterson",
                "stats": {
                    "strikeouts": 24,
                    "era": "5.06",
                    "ip": "26.2"
                }
            },
            "lineup_hash": "ed3531e2e10f4dd0c2512e0bfb47634c"
        },
        "824930": {
            "away_team": "Detroit Tigers",
            "home_team": "Atlanta Braves",
            "away_lineup": [],
            "home_lineup": [],
            "away_pitcher": {
                "id": 669373,
                "name": "Tarik Skubal",
                "stats": {
                    "strikeouts": 38,
                    "era": "2.72",
                    "ip": "36.1"
                }
            },
            "home_pitcher": {
                "id": 702275,
                "name": "JR Ritchie",
                "stats": {
                    "strikeouts": 7,
                    "era": "2.57",
                    "ip": "7.0"
                }
            },
            "lineup_hash": "de102ff6d9bb8f466305f097a1157444"
        },
        "823796": {
            "away_team": "Arizona Diamondbacks",
            "home_team": "Milwaukee Brewers",
            "away_lineup": [],
            "home_lineup": [],
            "away_pitcher": {
                "id": 593958,
                "name": "Eduardo Rodriguez",
                "stats": {
                    "strikeouts": 18,
                    "era": "2.89",
                    "ip": "28.0"
                }
            },
            "home_pitcher": {
                "id": 687075,
                "name": "Brandon Sproat",
                "stats": {
                    "strikeouts": 20,
                    "era": "6.45",
                    "ip": "22.1"
                }
            },
            "lineup_hash": "5049600d9c73962b195679f4028999fd"
        },
        "825015": {
            "away_team": "Kansas City Royals",
            "home_team": "Athletics",
            "away_lineup": [],
            "home_lineup": [],
            "away_pitcher": {
                "id": 608379,
                "name": "Michael Wacha",
                "stats": {
                    "strikeouts": 28,
                    "era": "2.51",
                    "ip": "32.1"
                }
            },
            "home_pitcher": {
                "id": 622663,
                "name": "Luis Severino",
                "stats": {
                    "strikeouts": 32,
                    "era": "5.17",
                    "ip": "31.1"
                }
            },
            "lineup_hash": "b0615a0c675ff23731529894f4bd8495"
        },
        "822821": {
            "away_team": "Boston Red Sox",
            "home_team": "Toronto Blue Jays",
            "away_lineup": [
                {
                    "id": 701350,
                    "name": "Roman Anthony",
                    "position": "LF",
                    "stats": {
                        "runs": 11,
                        "doubles": 3,
                        "triples": 1,
                        "home_runs": 1,
                        "hits": 19,
                        "steals": 2,
                        "rbi": 5
                    }
                },
                {
                    "id": 575929,
                    "name": "Willson Contreras",
                    "position": "1B",
                    "stats": {
                        "runs": 15,
                        "doubles": 3,
                        "triples": 0,
                        "home_runs": 6,
                        "hits": 26,
                        "steals": 0,
                        "rbi": 19
                    }
                },
                {
                    "id": 657136,
                    "name": "Connor Wong",
                    "position": "C",
                    "stats": {
                        "runs": 2,
                        "doubles": 5,
                        "triples": 0,
                        "home_runs": 0,
                        "hits": 9,
                        "steals": 1,
                        "rbi": 5
                    }
                },
                {
                    "id": 596115,
                    "name": "Trevor Story",
                    "position": "SS",
                    "stats": {
                        "runs": 11,
                        "doubles": 5,
                        "triples": 0,
                        "home_runs": 2,
                        "hits": 23,
                        "steals": 2,
                        "rbi": 17
                    }
                },
                {
                    "id": 677800,
                    "name": "Wilyer Abreu",
                    "position": "RF",
                    "stats": {
                        "runs": 15,
                        "doubles": 6,
                        "triples": 1,
                        "home_runs": 4,
                        "hits": 33,
                        "steals": 0,
                        "rbi": 13
                    }
                },
                {
                    "id": 655316,
                    "name": "Andruw Monasterio",
                    "position": "DH",
                    "stats": {
                        "runs": 5,
                        "doubles": 4,
                        "triples": 0,
                        "home_runs": 1,
                        "hits": 10,
                        "steals": 1,
                        "rbi": 8
                    }
                },
                {
                    "id": 643396,
                    "name": "Isiah Kiner-Falefa",
                    "position": "2B",
                    "stats": {
                        "runs": 5,
                        "doubles": 0,
                        "triples": 0,
                        "home_runs": 0,
                        "hits": 7,
                        "steals": 2,
                        "rbi": 3
                    }
                },
                {
                    "id": 702332,
                    "name": "Caleb Durbin",
                    "position": "3B",
                    "stats": {
                        "runs": 12,
                        "doubles": 6,
                        "triples": 0,
                        "home_runs": 1,
                        "hits": 16,
                        "steals": 3,
                        "rbi": 11
                    }
                },
                {
                    "id": 678882,
                    "name": "Ceddanne Rafaela",
                    "position": "CF",
                    "stats": {
                        "runs": 13,
                        "doubles": 4,
                        "triples": 2,
                        "home_runs": 1,
                        "hits": 25,
                        "steals": 0,
                        "rbi": 10
                    }
                }
            ],
            "home_lineup": [
                {
                    "id": 676391,
                    "name": "Ernie Clement",
                    "position": "2B",
                    "stats": {
                        "runs": 9,
                        "doubles": 13,
                        "triples": 0,
                        "home_runs": 0,
                        "hits": 36,
                        "steals": 1,
                        "rbi": 7
                    }
                },
                {
                    "id": 662139,
                    "name": "Daulton Varsho",
                    "position": "CF",
                    "stats": {
                        "runs": 10,
                        "doubles": 5,
                        "triples": 0,
                        "home_runs": 3,
                        "hits": 22,
                        "steals": 2,
                        "rbi": 7
                    }
                },
                {
                    "id": 665926,
                    "name": "Andr\u00e9s Gim\u00e9nez",
                    "position": "SS",
                    "stats": {
                        "runs": 9,
                        "doubles": 6,
                        "triples": 1,
                        "home_runs": 3,
                        "hits": 28,
                        "steals": 4,
                        "rbi": 16
                    }
                },
                {
                    "id": 678218,
                    "name": "Brandon Valenzuela",
                    "position": "C",
                    "stats": {
                        "runs": 2,
                        "doubles": 0,
                        "triples": 0,
                        "home_runs": 1,
                        "hits": 5,
                        "steals": 0,
                        "rbi": 2
                    }
                },
                {
                    "id": 682818,
                    "name": "Yohendrick Pinango",
                    "position": "DH",
                    "stats": {
                        "runs": 0,
                        "doubles": 0,
                        "triples": 0,
                        "home_runs": 0,
                        "hits": 1,
                        "steals": 0,
                        "rbi": 0
                    }
                },
                {
                    "id": 665489,
                    "name": "Vladimir Guerrero Jr.",
                    "position": "1B",
                    "stats": {
                        "runs": 16,
                        "doubles": 7,
                        "triples": 0,
                        "home_runs": 2,
                        "hits": 36,
                        "steals": 2,
                        "rbi": 15
                    }
                },
                {
                    "id": 660821,
                    "name": "Jes\u00fas S\u00e1nchez",
                    "position": "RF",
                    "stats": {
                        "runs": 10,
                        "doubles": 4,
                        "triples": 0,
                        "home_runs": 4,
                        "hits": 22,
                        "steals": 0,
                        "rbi": 15
                    }
                },
                {
                    "id": 664702,
                    "name": "Myles Straw",
                    "position": "LF",
                    "stats": {
                        "runs": 13,
                        "doubles": 2,
                        "triples": 0,
                        "home_runs": 1,
                        "hits": 13,
                        "steals": 1,
                        "rbi": 3
                    }
                },
                {
                    "id": 672960,
                    "name": "Kazuma Okamoto",
                    "position": "3B",
                    "stats": {
                        "runs": 12,
                        "doubles": 2,
                        "triples": 0,
                        "home_runs": 5,
                        "hits": 23,
                        "steals": 0,
                        "rbi": 13
                    }
                }
            ],
            "away_pitcher": {
                "id": 678394,
                "name": "Brayan Bello",
                "stats": {
                    "strikeouts": 15,
                    "era": "9.00",
                    "ip": "22.0"
                }
            },
            "home_pitcher": {
                "id": 641778,
                "name": "Eric Lauer",
                "stats": {
                    "strikeouts": 19,
                    "era": "6.75",
                    "ip": "22.2"
                }
            },
            "lineup_hash": "4d7bc5f1c179a0811200d42e224c527b"
        },
        "823958": {
            "away_team": "Miami Marlins",
            "home_team": "Los Angeles Dodgers",
            "away_lineup": [
                {
                    "id": 665923,
                    "name": "Esteury Ruiz",
                    "position": "LF",
                    "stats": {
                        "runs": 0,
                        "doubles": 0,
                        "triples": 0,
                        "home_runs": 0,
                        "hits": 0,
                        "steals": 0,
                        "rbi": 0
                    }
                },
                {
                    "id": 805300,
                    "name": "Jakob Marsee",
                    "position": "CF",
                    "stats": {
                        "runs": 18,
                        "doubles": 3,
                        "triples": 2,
                        "home_runs": 1,
                        "hits": 21,
                        "steals": 10,
                        "rbi": 8
                    }
                },
                {
                    "id": 669364,
                    "name": "Xavier Edwards",
                    "position": "2B",
                    "stats": {
                        "runs": 21,
                        "doubles": 6,
                        "triples": 2,
                        "home_runs": 1,
                        "hits": 37,
                        "steals": 4,
                        "rbi": 9
                    }
                },
                {
                    "id": 688363,
                    "name": "Graham Pauley",
                    "position": "3B",
                    "stats": {
                        "runs": 7,
                        "doubles": 6,
                        "triples": 0,
                        "home_runs": 1,
                        "hits": 13,
                        "steals": 1,
                        "rbi": 9
                    }
                },
                {
                    "id": 669065,
                    "name": "Kyle Stowers",
                    "position": "DH",
                    "stats": {
                        "runs": 4,
                        "doubles": 3,
                        "triples": 0,
                        "home_runs": 0,
                        "hits": 8,
                        "steals": 0,
                        "rbi": 1
                    }
                },
                {
                    "id": 689414,
                    "name": "Liam Hicks",
                    "position": "C",
                    "stats": {
                        "runs": 17,
                        "doubles": 3,
                        "triples": 0,
                        "home_runs": 6,
                        "hits": 28,
                        "steals": 1,
                        "rbi": 27
                    }
                },
                {
                    "id": 683357,
                    "name": "Owen Caissie",
                    "position": "RF",
                    "stats": {
                        "runs": 10,
                        "doubles": 6,
                        "triples": 0,
                        "home_runs": 2,
                        "hits": 18,
                        "steals": 1,
                        "rbi": 15
                    }
                },
                {
                    "id": 681393,
                    "name": "Connor Norby",
                    "position": "1B",
                    "stats": {
                        "runs": 7,
                        "doubles": 5,
                        "triples": 0,
                        "home_runs": 3,
                        "hits": 21,
                        "steals": 2,
                        "rbi": 10
                    }
                },
                {
                    "id": 672640,
                    "name": "Otto Lopez",
                    "position": "SS",
                    "stats": {
                        "runs": 20,
                        "doubles": 7,
                        "triples": 2,
                        "home_runs": 3,
                        "hits": 37,
                        "steals": 4,
                        "rbi": 12
                    }
                }
            ],
            "home_lineup": [
                {
                    "id": 687221,
                    "name": "Dalton Rushing",
                    "position": "C",
                    "stats": {
                        "runs": 13,
                        "doubles": 2,
                        "triples": 0,
                        "home_runs": 7,
                        "hits": 15,
                        "steals": 0,
                        "rbi": 16
                    }
                },
                {
                    "id": 663656,
                    "name": "Kyle Tucker",
                    "position": "RF",
                    "stats": {
                        "runs": 20,
                        "doubles": 5,
                        "triples": 0,
                        "home_runs": 3,
                        "hits": 27,
                        "steals": 3,
                        "rbi": 15
                    }
                },
                {
                    "id": 571970,
                    "name": "Max Muncy",
                    "position": "3B",
                    "stats": {
                        "runs": 22,
                        "doubles": 3,
                        "triples": 0,
                        "home_runs": 9,
                        "hits": 28,
                        "steals": 0,
                        "rbi": 11
                    }
                },
                {
                    "id": 518692,
                    "name": "Freddie Freeman",
                    "position": "1B",
                    "stats": {
                        "runs": 11,
                        "doubles": 7,
                        "triples": 1,
                        "home_runs": 3,
                        "hits": 30,
                        "steals": 0,
                        "rbi": 15
                    }
                },
                {
                    "id": 808975,
                    "name": "Hyeseong Kim",
                    "position": "SS",
                    "stats": {
                        "runs": 7,
                        "doubles": 2,
                        "triples": 0,
                        "home_runs": 1,
                        "hits": 15,
                        "steals": 5,
                        "rbi": 7
                    }
                },
                {
                    "id": 660271,
                    "name": "Shohei Ohtani",
                    "position": "DH",
                    "stats": {
                        "runs": 21,
                        "doubles": 6,
                        "triples": 0,
                        "home_runs": 6,
                        "hits": 30,
                        "steals": 3,
                        "rbi": 13
                    }
                },
                {
                    "id": 681624,
                    "name": "Andy Pages",
                    "position": "CF",
                    "stats": {
                        "runs": 16,
                        "doubles": 7,
                        "triples": 0,
                        "home_runs": 5,
                        "hits": 35,
                        "steals": 4,
                        "rbi": 25
                    }
                },
                {
                    "id": 669743,
                    "name": "Alex Call",
                    "position": "LF",
                    "stats": {
                        "runs": 6,
                        "doubles": 2,
                        "triples": 0,
                        "home_runs": 0,
                        "hits": 8,
                        "steals": 0,
                        "rbi": 2
                    }
                },
                {
                    "id": 690976,
                    "name": "Alex Freeland",
                    "position": "2B",
                    "stats": {
                        "runs": 8,
                        "doubles": 4,
                        "triples": 0,
                        "home_runs": 1,
                        "hits": 17,
                        "steals": 0,
                        "rbi": 6
                    }
                }
            ],
            "away_pitcher": {
                "id": 645261,
                "name": "Sandy Alcantara",
                "stats": {
                    "strikeouts": 27,
                    "era": "3.05",
                    "ip": "41.1"
                }
            },
            "home_pitcher": {
                "id": 607192,
                "name": "Tyler Glasnow",
                "stats": {
                    "strikeouts": 38,
                    "era": "2.45",
                    "ip": "33.0"
                }
            },
            "lineup_hash": "463f6b649a003a3a2d9d1ba329aca348"
        },
        "823312": {
            "away_team": "Chicago Cubs",
            "home_team": "San Diego Padres",
            "away_lineup": [
                {
                    "id": 624424,
                    "name": "Michael Conforto",
                    "position": "RF",
                    "stats": {
                        "runs": 3,
                        "doubles": 3,
                        "triples": 0,
                        "home_runs": 0,
                        "hits": 8,
                        "steals": 0,
                        "rbi": 5
                    }
                },
                {
                    "id": 664023,
                    "name": "Ian Happ",
                    "position": "LF",
                    "stats": {
                        "runs": 20,
                        "doubles": 4,
                        "triples": 0,
                        "home_runs": 7,
                        "hits": 25,
                        "steals": 1,
                        "rbi": 14
                    }
                },
                {
                    "id": 608324,
                    "name": "Alex Bregman",
                    "position": "3B",
                    "stats": {
                        "runs": 10,
                        "doubles": 3,
                        "triples": 1,
                        "home_runs": 3,
                        "hits": 31,
                        "steals": 1,
                        "rbi": 11
                    }
                },
                {
                    "id": 683737,
                    "name": "Michael Busch",
                    "position": "1B",
                    "stats": {
                        "runs": 14,
                        "doubles": 4,
                        "triples": 0,
                        "home_runs": 2,
                        "hits": 22,
                        "steals": 0,
                        "rbi": 11
                    }
                },
                {
                    "id": 691718,
                    "name": "Pete Crow-Armstrong",
                    "position": "CF",
                    "stats": {
                        "runs": 18,
                        "doubles": 3,
                        "triples": 1,
                        "home_runs": 2,
                        "hits": 27,
                        "steals": 6,
                        "rbi": 10
                    }
                },
                {
                    "id": 665804,
                    "name": "Miguel Amaya",
                    "position": "C",
                    "stats": {
                        "runs": 10,
                        "doubles": 1,
                        "triples": 0,
                        "home_runs": 2,
                        "hits": 11,
                        "steals": 0,
                        "rbi": 5
                    }
                },
                {
                    "id": 694208,
                    "name": "Mois\u00e9s Ballesteros",
                    "position": "DH",
                    "stats": {
                        "runs": 12,
                        "doubles": 5,
                        "triples": 0,
                        "home_runs": 5,
                        "hits": 24,
                        "steals": 0,
                        "rbi": 16
                    }
                },
                {
                    "id": 663538,
                    "name": "Nico Hoerner",
                    "position": "SS",
                    "stats": {
                        "runs": 16,
                        "doubles": 8,
                        "triples": 0,
                        "home_runs": 4,
                        "hits": 36,
                        "steals": 7,
                        "rbi": 26
                    }
                },
                {
                    "id": 807713,
                    "name": "Matt Shaw",
                    "position": "2B",
                    "stats": {
                        "runs": 8,
                        "doubles": 5,
                        "triples": 0,
                        "home_runs": 2,
                        "hits": 19,
                        "steals": 2,
                        "rbi": 9
                    }
                }
            ],
            "home_lineup": [
                {
                    "id": 669134,
                    "name": "Luis Campusano",
                    "position": "C",
                    "stats": {
                        "runs": 8,
                        "doubles": 7,
                        "triples": 0,
                        "home_runs": 3,
                        "hits": 15,
                        "steals": 0,
                        "rbi": 10
                    }
                },
                {
                    "id": 592206,
                    "name": "Nick Castellanos",
                    "position": "LF",
                    "stats": {
                        "runs": 1,
                        "doubles": 3,
                        "triples": 0,
                        "home_runs": 0,
                        "hits": 8,
                        "steals": 0,
                        "rbi": 7
                    }
                },
                {
                    "id": 701538,
                    "name": "Jackson Merrill",
                    "position": "CF",
                    "stats": {
                        "runs": 19,
                        "doubles": 6,
                        "triples": 0,
                        "home_runs": 3,
                        "hits": 23,
                        "steals": 5,
                        "rbi": 15
                    }
                },
                {
                    "id": 592518,
                    "name": "Manny Machado",
                    "position": "DH",
                    "stats": {
                        "runs": 18,
                        "doubles": 4,
                        "triples": 0,
                        "home_runs": 4,
                        "hits": 22,
                        "steals": 1,
                        "rbi": 16
                    }
                },
                {
                    "id": 609280,
                    "name": "Miguel Andujar",
                    "position": "3B",
                    "stats": {
                        "runs": 6,
                        "doubles": 6,
                        "triples": 1,
                        "home_runs": 0,
                        "hits": 20,
                        "steals": 1,
                        "rbi": 6
                    }
                },
                {
                    "id": 664034,
                    "name": "Ty France",
                    "position": "1B",
                    "stats": {
                        "runs": 8,
                        "doubles": 2,
                        "triples": 1,
                        "home_runs": 3,
                        "hits": 13,
                        "steals": 1,
                        "rbi": 8
                    }
                },
                {
                    "id": 665487,
                    "name": "Fernando Tatis Jr.",
                    "position": "RF",
                    "stats": {
                        "runs": 11,
                        "doubles": 4,
                        "triples": 0,
                        "home_runs": 0,
                        "hits": 27,
                        "steals": 7,
                        "rbi": 12
                    }
                },
                {
                    "id": 593428,
                    "name": "Xander Bogaerts",
                    "position": "SS",
                    "stats": {
                        "runs": 14,
                        "doubles": 2,
                        "triples": 0,
                        "home_runs": 5,
                        "hits": 30,
                        "steals": 3,
                        "rbi": 17
                    }
                },
                {
                    "id": 630105,
                    "name": "Jake Cronenworth",
                    "position": "2B",
                    "stats": {
                        "runs": 12,
                        "doubles": 2,
                        "triples": 0,
                        "home_runs": 1,
                        "hits": 13,
                        "steals": 1,
                        "rbi": 4
                    }
                }
            ],
            "away_pitcher": {
                "id": 592791,
                "name": "Jameson Taillon",
                "stats": {
                    "strikeouts": 25,
                    "era": "4.55",
                    "ip": "27.2"
                }
            },
            "home_pitcher": {
                "id": 663362,
                "name": "Matt Waldron",
                "stats": {
                    "strikeouts": 7,
                    "era": "12.46",
                    "ip": "8.2"
                }
            },
            "lineup_hash": "48e4966590cd48abb9a423eaf29138ce"
        },
        "824525": {
            "away_team": "Colorado Rockies",
            "home_team": "Cincinnati Reds",
            "away_lineup": [
                {
                    "id": 666160,
                    "name": "Mickey Moniak",
                    "position": "RF",
                    "stats": {
                        "runs": 14,
                        "doubles": 5,
                        "triples": 0,
                        "home_runs": 8,
                        "hits": 26,
                        "steals": 1,
                        "rbi": 15
                    }
                },
                {
                    "id": 650489,
                    "name": "Willi Castro",
                    "position": "2B",
                    "stats": {
                        "runs": 10,
                        "doubles": 4,
                        "triples": 0,
                        "home_runs": 1,
                        "hits": 17,
                        "steals": 2,
                        "rbi": 9
                    }
                },
                {
                    "id": 696100,
                    "name": "Hunter Goodman",
                    "position": "DH",
                    "stats": {
                        "runs": 19,
                        "doubles": 6,
                        "triples": 0,
                        "home_runs": 7,
                        "hits": 25,
                        "steals": 1,
                        "rbi": 11
                    }
                },
                {
                    "id": 687597,
                    "name": "Jordan Beck",
                    "position": "LF",
                    "stats": {
                        "runs": 4,
                        "doubles": 2,
                        "triples": 0,
                        "home_runs": 1,
                        "hits": 9,
                        "steals": 2,
                        "rbi": 7
                    }
                },
                {
                    "id": 664954,
                    "name": "Brett Sullivan",
                    "position": "C",
                    "stats": {
                        "runs": 1,
                        "doubles": 4,
                        "triples": 0,
                        "home_runs": 0,
                        "hits": 10,
                        "steals": 0,
                        "rbi": 4
                    }
                },
                {
                    "id": 686668,
                    "name": "Brenton Doyle",
                    "position": "CF",
                    "stats": {
                        "runs": 11,
                        "doubles": 2,
                        "triples": 0,
                        "home_runs": 1,
                        "hits": 16,
                        "steals": 6,
                        "rbi": 2
                    }
                },
                {
                    "id": 678662,
                    "name": "Ezequiel Tovar",
                    "position": "SS",
                    "stats": {
                        "runs": 8,
                        "doubles": 8,
                        "triples": 0,
                        "home_runs": 1,
                        "hits": 21,
                        "steals": 2,
                        "rbi": 6
                    }
                },
                {
                    "id": 681198,
                    "name": "TJ Rumfield",
                    "position": "1B",
                    "stats": {
                        "runs": 9,
                        "doubles": 5,
                        "triples": 1,
                        "home_runs": 3,
                        "hits": 27,
                        "steals": 0,
                        "rbi": 16
                    }
                },
                {
                    "id": 691720,
                    "name": "Kyle Karros",
                    "position": "3B",
                    "stats": {
                        "runs": 12,
                        "doubles": 3,
                        "triples": 0,
                        "home_runs": 1,
                        "hits": 16,
                        "steals": 2,
                        "rbi": 3
                    }
                }
            ],
            "home_lineup": [],
            "away_pitcher": {
                "id": 608372,
                "name": "Tomoyuki Sugano",
                "stats": {
                    "strikeouts": 19,
                    "era": "3.42",
                    "ip": "26.1"
                }
            },
            "home_pitcher": {
                "id": 682227,
                "name": "Brandon Williamson",
                "stats": {
                    "strikeouts": 15,
                    "era": "5.40",
                    "ip": "25.0"
                }
            },
            "lineup_hash": "e2daf5198689aa452d8a70834fb9ded2"
        }
    }
}